gardening_tools/functional/__init__.py
gardening_tools/functional/metrics.py
gardening_tools/functional/nibabel_utils.py
gardening_tools/functional/normalization.py
gardening_tools/functional/sanity_checks.py
gardening_tools/functional/type_conversions.py
gardening_tools/functional/paths/__init__.py
gardening_tools/functional/paths/read.py
gardening_tools/functional/paths/scan.py
gardening_tools/functional/paths/write.py
gardening_tools/functional/transforms/__init__.py
gardening_tools/functional/transforms/bias_field.py
gardening_tools/functional/transforms/blur.py
gardening_tools/functional/transforms/cropping_and_padding.py
gardening_tools/functional/transforms/gamma.py
gardening_tools/functional/transforms/masking.py
gardening_tools/functional/transforms/motion_ghosting.py
gardening_tools/functional/transforms/noise.py
gardening_tools/functional/transforms/ringing.py
gardening_tools/functional/transforms/sampling.py
gardening_tools/functional/transforms/spatial.py
gardening_tools/modules/__init__.py
gardening_tools/modules/metrics.py
gardening_tools/modules/losses/CE.py
gardening_tools/modules/losses/Dice.py
gardening_tools/modules/losses/DiceCE.py
gardening_tools/modules/losses/__init__.py
gardening_tools/modules/losses/deep_supervision.py
gardening_tools/modules/networks/BaseNet.py
gardening_tools/modules/networks/__init__.py
gardening_tools/modules/networks/primus.py
gardening_tools/modules/networks/resunet.py
gardening_tools/modules/networks/unet.py
gardening_tools/modules/networks/utils.py
gardening_tools/modules/networks/components/__init__.py
gardening_tools/modules/networks/components/blocks.py
gardening_tools/modules/networks/components/decoders.py
gardening_tools/modules/networks/components/encoders.py
gardening_tools/modules/networks/components/eva.py
gardening_tools/modules/networks/components/heads.py
gardening_tools/modules/networks/components/layers.py
gardening_tools/modules/networks/components/transformer.py
gardening_tools-0.2.0.dist-info/licenses/LICENSE
gardening_tools-0.2.0.dist-info/METADATA
gardening_tools-0.2.0.dist-info/WHEEL
gardening_tools-0.2.0.dist-info/top_level.txt
gardening_tools-0.2.0.dist-info/RECORD
