Metadata-Version: 2.4
Name: gardening_tools
Version: 0.2.0
Author-email: Sebastian Llambias <llambias@live.com>
License: Apache-2.0
Project-URL: Homepage, https://github.com/Sllambias/gardening_tools
Keywords: gardening tools,plant care,garden management
Classifier: Programming Language :: Python :: 3
Requires-Python: >=3.11
License-File: LICENSE
Requires-Dist: torch>=2.6.0
Requires-Dist: numpy>=2.2.5
Requires-Dist: nibabel>=5.3.2
Requires-Dist: scipy>=1.16.3
Requires-Dist: scikit-image>=0.22.0
Provides-Extra: extras
Requires-Dist: timm>=1.0.22; extra == "extras"
Requires-Dist: einops>=0.8.1; extra == "extras"
Dynamic: license-file
